livestatus_objects
