Metadata-Version: 1.1
Name: livestatus-objects
Version: 0.4
Summary: Query MK Livestatus and return results as objects.
Home-page: http://github.com/sysnove/livestatus-objects
Author: Guillaume Subiron
Author-email: maethor+pip@subiron.org
License: WTFPL
Platform: UNKNOWN
Classifier: Programming Language :: Python
Classifier: Operating System :: OS Independent
Classifier: Intended Audience :: Developers
Classifier: Intended Audience :: System Administrators
Classifier: Programming Language :: Python :: 3.3
